MANIFEST.in
README
setup.py
bin/me2
bin/me2-fleet
bin/me2-init
bin/me2-irc
bin/me2-release
bin/me2-rollback
bin/me2-run
bin/me2-stop
bin/me2-udp
bin/me2-upload
bin/me2-uploadall
bin/me2-xmpp
me2/__init__.py
me2.egg-info/PKG-INFO
me2.egg-info/SOURCES.txt
me2.egg-info/dependency_links.txt
me2.egg-info/top_level.txt
me2/contrib/__init__.py
me2/contrib/feedparser.py
me2/contrib/oauth.py
me2/contrib/oauthtwitter.py
me2/contrib/rijndael.py
me2/contrib/xmlstream.py
me2/contrib/simplejson/__init__.py
me2/contrib/simplejson/decoder.py
me2/contrib/simplejson/encoder.py
me2/contrib/simplejson/ordered_dict.py
me2/contrib/simplejson/scanner.py
me2/contrib/simplejson/tool.py
me2/contrib/tweepy/__init__.py
me2/contrib/tweepy/api.py
me2/contrib/tweepy/auth.py
me2/contrib/tweepy/binder.py
me2/contrib/tweepy/cache.py
me2/contrib/tweepy/cursor.py
me2/contrib/tweepy/error.py
me2/contrib/tweepy/models.py
me2/contrib/tweepy/oauth.py
me2/contrib/tweepy/parsers.py
me2/contrib/tweepy/streaming.py
me2/contrib/tweepy/utils.py
me2/data/examples/README
me2/data/examples/__init__.py
me2/data/examples/app.yaml.example
me2/data/examples/credentials.py.example
me2/data/examples/cron.yaml.example
me2/data/examples/mainconfig.example
me2/data/examples/queue.yaml.example
me2/lib/__init__.py
me2/lib/boot.py
me2/lib/botbase.py
me2/lib/cache.py
me2/lib/callbacks.py
me2/lib/channelbase.py
me2/lib/commands.py
me2/lib/config.py
me2/lib/container.py
me2/lib/datadir.py
me2/lib/errors.py
me2/lib/eventbase.py
me2/lib/eventhandler.py
me2/lib/examples.py
me2/lib/exit.py
me2/lib/factory.py
me2/lib/fleet.py
me2/lib/gatekeeper.py
me2/lib/gozerevent.py
me2/lib/less.py
me2/lib/me2import.py
me2/lib/morphs.py
me2/lib/outputcache.py
me2/lib/persist.py
me2/lib/persistconfig.py
me2/lib/persiststate.py
me2/lib/plugins.py
me2/lib/reboot.py
me2/lib/runner.py
me2/lib/tasks.py
me2/lib/threadloop.py
me2/lib/threads.py
me2/lib/tick.py
me2/lib/users.py
me2/lib/version.py
me2/lib/console/__init__.py
me2/lib/console/bot.py
me2/lib/console/event.py
me2/lib/gae/__init__.py
me2/lib/gae/tasks.py
me2/lib/gae/utils/__init__.py
