Metadata-Version: 1.0
Name: me2
Version: 0.1a1
Summary: The bot for you!
Home-page: http://botme2.googlecode.com/
Author: Bart Thate
Author-email: bthate@gmail.com
License: MIT
Download-URL: http://code.google.com/p/botme2/downloads
Platform: UNKNOWN
Classifier: Development Status :: 3 - Alpha
Classifier: Environment :: Console
Classifier: Environment :: Other Environment
Classifier: Intended Audience :: Developers
Classifier: License :: OSI Approved :: MIT License
Classifier: Operating System :: Unix
Classifier: Operating System :: Other OS
Classifier: Programming Language :: Python
Classifier: Topic :: Communications :: Chat
Classifier: Topic :: Software Development :: Libraries :: Python Modules
